ewox/__init__.py
ewox-1.8.54.dist-info/METADATA
ewox-1.8.54.dist-info/WHEEL
ewox-1.8.54.dist-info/licenses/LICENSE
ewox-1.8.54.dist-info/RECORD
