Metadata-Version: 2.4
Name: ewox
Version: 1.8.54
Summary: 
License-File: LICENSE
Author: Martin Leo Prüss
Author-email: mleopruss@gmail.com
Requires-Python: >=3.9.18, <4.0
Classifier: Programming Language :: Python :: 3
Classifier: Programming Language :: Python :: 3.10
Classifier: Programming Language :: Python :: 3.11
Classifier: Programming Language :: Python :: 3.12
Classifier: Programming Language :: Python :: 3.13
Classifier: Programming Language :: Python :: 3.14
Requires-Dist: ewoxcore (>=1.6.3,<2.0.0)
Requires-Dist: ewoxdbgraph (>=1.2.0,<2.0.0)
Requires-Dist: ewoxdbredis (>=1.2.7,<2.0.0)
Requires-Dist: ewoxservicefastapi (>=1.7.2,<2.0.0)
